setup.cfg
setup.py
vimap/__init__.py
vimap/chunked_real_worker_routine.py
vimap/config.py
vimap/exception_handling.py
vimap/pool.py
vimap/queue_manager.py
vimap/real_worker_routine.py
vimap/testing.py
vimap/util.py
vimap/worker_process.py
vimap.egg-info/PKG-INFO
vimap.egg-info/SOURCES.txt
vimap.egg-info/dependency_links.txt
vimap.egg-info/top_level.txt
vimap/ext/__init__.py
vimap/ext/file_runner.py
vimap/ext/sugar.py
vimap/ext/vimap_fold.py