Metadata-Version: 1.1
Name: vimap
Version: 0.1.9-alpha-deadlock-quickfix
Summary: vimap
Home-page: https://github.com/gatoatigrado/vimap
Author: gatoatigrado
Author-email: gatoatigrado@gmail.com
License: UNKNOWN
Platform: UNKNOWN
Classifier: Programming Language :: Python
Classifier: Operating System :: OS Independent
Classifier: License :: OSI Approved :: Apache Software License
Classifier: Topic :: Software Development :: Libraries :: Python Modules
Classifier: Intended Audience :: Developers
Classifier: Development Status :: 3 - Alpha
Provides: vimap
